figgy/__init__.py
figgy/make.py
figgy-0.1.2.dev2.dist-info/DESCRIPTION.rst
figgy-0.1.2.dev2.dist-info/METADATA
figgy-0.1.2.dev2.dist-info/RECORD
figgy-0.1.2.dev2.dist-info/WHEEL
figgy-0.1.2.dev2.dist-info/metadata.json
figgy-0.1.2.dev2.dist-info/top_level.txt
tests/__init__.py
tests/test_make.py
