Metadata-Version: 2.0
Name: figgy
Version: 0.1.2.dev2
Summary: Prompt-based end-user configuration generator.
Home-page: https://github.com/dyspop/figgy
Author: Dan Black
Author-email: dyspop@gmail.com
License: GPL-3.0+
Download-URL: https://github.com/dyspop/figgy/archive/0.1.2.dev2.tar.gz
Keywords: config,configuration,generator,configuration generator,dev tool,json,tty,cli-like
Platform: UNKNOWN
Classifier: Development Status :: 3 - Alpha
Classifier: Intended Audience :: Developers
Classifier: Topic :: Software Development :: Build Tools
Classifier: License :: OSI Approved :: GNU General Public License v3 or later (GPLv3+)
Classifier: Programming Language :: Python :: 3
Classifier: Programming Language :: Python :: 3.2
Classifier: Programming Language :: Python :: 3.3
Classifier: Programming Language :: Python :: 3.4
Classifier: Programming Language :: Python :: 3.5
Classifier: Programming Language :: Python :: 3.6
